{
  "name_to_code": {
    "shopping_net": 13,
    "misc_pos": 13,
    "shopping_pos": 13,
    "grocery_net": 13,
    "misc_net": 13,
    "grocery_pos": 13,
    "gas_transport": 13,
    "entertainment": 13,
    "kids_pets": 13,
    "food_dining": 13,
    "personal_care": 13,
    "home": 13,
    "travel": 13,
    "health_fitness": 13
  },
  "code_to_name": {
    "0": "health_fitness",
    "1": "kids_pets",
    "2": "grocery_pos",
    "3": "misc_net",
    "4": "home",
    "5": "gas_transport",
    "6": "travel",
    "7": "personal_care",
    "8": "food_dining",
    "9": "personal_care",
    "10": "grocery_net",
    "11": "health_fitness",
    "12": "misc_net",
    "13": "grocery_net"
  },
  "frequency": {
    "gas_transport": 131659,
    "grocery_pos": 123638,
    "home": 123115,
    "shopping_pos": 116672,
    "kids_pets": 113035,
    "shopping_net": 97543,
    "entertainment": 94014,
    "food_dining": 91461,
    "personal_care": 90758,
    "health_fitness": 85879,
    "misc_pos": 79655,
    "misc_net": 63287,
    "grocery_net": 45452,
    "travel": 40507
  },
  "total_transactions": 1296675,
  "top5_common": [
    "gas_transport",
    "grocery_pos",
    "home",
    "shopping_pos",
    "kids_pets"
  ],
  "categories_list": [
    "shopping_net",
    "misc_pos",
    "shopping_pos",
    "grocery_net",
    "misc_net",
    "grocery_pos",
    "gas_transport",
    "entertainment",
    "kids_pets",
    "food_dining",
    "personal_care",
    "home",
    "travel",
    "health_fitness",
    "shopping_pos",
    "misc_net",
    "shopping_net",
    "misc_pos",
    "entertainment",
    "travel",
    "health_fitness",
    "grocery_net",
    "gas_transport",
    "grocery_pos",
    "food_dining",
    "home",
    "personal_care",
    "kids_pets",
    "grocery_net",
    "travel",
    "personal_care",
    "shopping_pos",
    "kids_pets",
    "food_dining",
    "misc_net",
    "shopping_net",
    "misc_pos",
    "gas_transport",
    "entertainment",
    "home",
    "health_fitness",
    "grocery_pos",
    "grocery_pos",
    "shopping_net",
    "shopping_pos",
    "health_fitness",
    "grocery_net",
    "gas_transport",
    "misc_pos",
    "entertainment",
    "travel",
    "food_dining",
    "kids_pets",
    "personal_care",
    "home",
    "misc_net",
    "misc_pos",
    "shopping_pos",
    "entertainment",
    "personal_care",
    "shopping_net",
    "misc_net",
    "grocery_net",
    "gas_transport",
    "kids_pets",
    "food_dining",
    "grocery_pos",
    "travel",
    "health_fitness",
    "home",
    "shopping_net",
    "entertainment",
    "personal_care",
    "health_fitness",
    "home",
    "travel",
    "kids_pets",
    "food_dining",
    "misc_pos",
    "grocery_net",
    "shopping_pos",
    "grocery_pos",
    "misc_net",
    "gas_transport",
    "grocery_pos",
    "kids_pets",
    "health_fitness",
    "home",
    "entertainment",
    "shopping_net",
    "food_dining",
    "grocery_net",
    "misc_net",
    "shopping_pos",
    "gas_transport",
    "misc_pos",
    "personal_care",
    "travel",
    "home",
    "travel",
    "kids_pets",
    "misc_pos",
    "misc_net",
    "health_fitness",
    "shopping_net",
    "shopping_pos",
    "grocery_pos",
    "gas_transport",
    "grocery_net",
    "food_dining",
    "entertainment",
    "personal_care",
    "grocery_pos",
    "grocery_net",
    "shopping_net",
    "gas_transport",
    "entertainment",
    "misc_pos",
    "misc_net",
    "shopping_pos",
    "travel",
    "personal_care",
    "kids_pets",
    "home",
    "health_fitness",
    "food_dining",
    "grocery_pos",
    "grocery_net",
    "health_fitness",
    "kids_pets",
    "misc_pos",
    "gas_transport",
    "shopping_net",
    "shopping_pos",
    "misc_net",
    "food_dining",
    "travel",
    "home",
    "entertainment",
    "personal_care",
    "grocery_pos",
    "misc_pos",
    "health_fitness",
    "kids_pets",
    "home",
    "personal_care",
    "shopping_pos",
    "misc_net",
    "entertainment",
    "shopping_net",
    "food_dining",
    "travel",
    "gas_transport",
    "grocery_net",
    "misc_pos",
    "shopping_pos",
    "food_dining",
    "grocery_pos",
    "gas_transport",
    "misc_net",
    "grocery_net",
    "entertainment",
    "shopping_net",
    "travel",
    "personal_care",
    "home",
    "kids_pets",
    "health_fitness",
    "misc_pos",
    "grocery_pos",
    "shopping_net",
    "shopping_pos",
    "grocery_net",
    "gas_transport",
    "health_fitness",
    "entertainment",
    "travel",
    "kids_pets",
    "food_dining",
    "personal_care",
    "home",
    "misc_net",
    "grocery_pos",
    "shopping_net",
    "misc_pos",
    "food_dining",
    "gas_transport",
    "home",
    "entertainment",
    "misc_net",
    "travel",
    "health_fitness",
    "shopping_pos",
    "kids_pets",
    "personal_care",
    "grocery_net"
  ]
}